CHANGELOG.txt
LICENSE.txt
MANIFEST.in
README.txt
setup.py
currencypairs/__init__.py
currencypairs/audusd.py
currencypairs/gbpeur.py
currencypairs/main.py
currencypairs/usdinr.py
currencypairs.egg-info/PKG-INFO
currencypairs.egg-info/SOURCES.txt
currencypairs.egg-info/dependency_links.txt
currencypairs.egg-info/requires.txt
currencypairs.egg-info/top_level.txt