Metadata-Version: 2.1
Name: currencypairs
Version: 0.0.1
Summary: Classes for storing data for currency pairs
Home-page: 
Author: Surbhi Gupta
Author-email: sg7319@nyu.edu
License: MIT
Classifier: Intended Audience :: Developers
Classifier: License :: OSI Approved :: MIT License
Classifier: Programming Language :: Python
Classifier: Programming Language :: Python :: 3
Classifier: Programming Language :: Python :: 3.6
Classifier: Programming Language :: Python :: 3.7
Classifier: Programming Language :: Python :: 3.8
Classifier: Programming Language :: Python :: 3.9
Classifier: Operating System :: OS Independent
License-File: LICENSE.txt
